aiida_quantumespresso/__init__.py
aiida_quantumespresso/calculations/__init__.py
aiida_quantumespresso/calculations/bands.py
aiida_quantumespresso/calculations/base.py
aiida_quantumespresso/calculations/cp.py
aiida_quantumespresso/calculations/dos.py
aiida_quantumespresso/calculations/epw.py
aiida_quantumespresso/calculations/matdyn.py
aiida_quantumespresso/calculations/namelists.py
aiida_quantumespresso/calculations/neb.py
aiida_quantumespresso/calculations/open_grid.py
aiida_quantumespresso/calculations/ph.py
aiida_quantumespresso/calculations/pp.py
aiida_quantumespresso/calculations/projwfc.py
aiida_quantumespresso/calculations/pw.py
aiida_quantumespresso/calculations/pw2gw.py
aiida_quantumespresso/calculations/pw2wannier90.py
aiida_quantumespresso/calculations/pwimmigrant.py
aiida_quantumespresso/calculations/q2r.py
aiida_quantumespresso/calculations/xspectra.py
aiida_quantumespresso/calculations/functions/__init__.py
aiida_quantumespresso/calculations/functions/create_kpoints_from_distance.py
aiida_quantumespresso/calculations/functions/create_magnetic_configuration.py
aiida_quantumespresso/calculations/functions/merge_ph_outputs.py
aiida_quantumespresso/calculations/functions/seekpath_structure_analysis.py
aiida_quantumespresso/calculations/functions/xspectra/__init__.py
aiida_quantumespresso/calculations/functions/xspectra/get_powder_spectrum.py
aiida_quantumespresso/calculations/functions/xspectra/get_spectra_by_element.py
aiida_quantumespresso/calculations/functions/xspectra/get_xps_spectra.py
aiida_quantumespresso/calculations/functions/xspectra/merge_spectra.py
aiida_quantumespresso/calculations/helpers/INPUT_PW-5.0.1.xml
aiida_quantumespresso/calculations/helpers/INPUT_PW-5.0.2.xml
aiida_quantumespresso/calculations/helpers/INPUT_PW-5.0.3.xml
aiida_quantumespresso/calculations/helpers/INPUT_PW-5.0.xml
aiida_quantumespresso/calculations/helpers/INPUT_PW-5.1.1.xml
aiida_quantumespresso/calculations/helpers/INPUT_PW-5.1.2.xml
aiida_quantumespresso-4.16.0.dist-info/METADATA
aiida_quantumespresso-4.16.0.dist-info/WHEEL
aiida_quantumespresso-4.16.0.dist-info/entry_points.txt
aiida_quantumespresso-4.16.0.dist-info/licenses/LICENSE.txt
aiida_quantumespresso-4.16.0.dist-info/RECORD
