Metadata-Version: 2.4
Name: aiida-quantumespresso
Version: 4.16.0
Summary: The official AiiDA plugin for Quantum ESPRESSO
Project-URL: Home, https://github.com/aiidateam/aiida-quantumespresso
Project-URL: Source, https://github.com/aiidateam/aiida-quantumespresso
Project-URL: Documentation, https://aiida-quantumespresso.readthedocs.io
Author-email: The AiiDA team <developers@aiida.net>
License: The MIT License (MIT)
License-File: LICENSE.txt
Keywords: aiida,workflows
Classifier: Development Status :: 5 - Production/Stable
Classifier: Framework :: AiiDA
Classifier: License :: OSI Approved :: MIT License
Classifier: Programming Language :: Python
Classifier: Programming Language :: Python :: 3.10
Classifier: Programming Language :: Python :: 3.11
Classifier: Programming Language :: Python :: 3.12
Classifier: Programming Language :: Python :: 3.13
Classifier: Programming Language :: Python :: 3.14
Requires-Python: >=3.10
Requires-Dist: aiida-core[atomic-tools]~=2.3
Requires-Dist: aiida-pseudo<2,>=1.7.2
Requires-Dist: click~=8.0
Requires-Dist: importlib-resources
Requires-Dist: jsonschema
Requires-Dist: numpy
Requires-Dist: packaging
Requires-Dist: pydantic~=2.0
Requires-Dist: qe-tools~=2.0
Requires-Dist: xmlschema~=2.0
Provides-Extra: docs
Requires-Dist: myst-parser~=3.0.0; extra == 'docs'
Requires-Dist: sphinx-autoapi~=3.0.0; extra == 'docs'
Requires-Dist: sphinx-book-theme~=1.0.1; extra == 'docs'
Requires-Dist: sphinx-click~=4.4.0; extra == 'docs'
Requires-Dist: sphinx-copybutton~=0.5.2; extra == 'docs'
Requires-Dist: sphinx-design~=0.4.1; extra == 'docs'
Requires-Dist: sphinxcontrib-details-directive~=0.1.0; extra == 'docs'
Requires-Dist: sphinx~=6.2.1; extra == 'docs'
Provides-Extra: pre-commit
Requires-Dist: pre-commit>=4.3.0; extra == 'pre-commit'
Provides-Extra: tests
Requires-Dist: pgtest~=1.3; extra == 'tests'
Requires-Dist: pytest-regressions~=2.8; extra == 'tests'
Requires-Dist: pytest~=8.4; extra == 'tests'
